Metadata-Version: 2.1
Name: model-insight
Version: 0.67
Summary: A package for learning and teaching mathematical modeling
Home-page: https://reformship.github.io/pages(en)/134modelinsight.html
Author: Wang Haihua
Author-email: reformship@gmail.com
License: MIT
Project-URL: Documentation(Chinese), https://reformship.github.io/pages/134modelinsight.html
Project-URL: Code, https://github.com/reformship/model-insight
Project-URL: Issue tracker, https://github.com/reformship/model-insight/issues
Keywords: mathematical modeling
Platform: UNKNOWN
